aonsq/__init__.py
aonsq/cli.py
aonsq/cli_basic.py
aonsq/message.py
aonsq/utils.py
aonsq-0.1.9.dist-info/LICENSE
aonsq-0.1.9.dist-info/METADATA
aonsq-0.1.9.dist-info/WHEEL
aonsq-0.1.9.dist-info/top_level.txt
aonsq-0.1.9.dist-info/RECORD
