Metadata-Version: 2.1
Name: aonsq
Version: 0.1.9
Summary: nsq client library
Home-page: https://github.com/SCys/aonsq
Author: SCys
Author-email: me@iscys.com
License: UNKNOWN
Platform: UNKNOWN
Classifier: Development Status :: 3 - Alpha
Classifier: Topic :: Software Development :: Libraries
Classifier: License :: OSI Approved :: Apache Software License
Classifier: Operating System :: OS Independent
Classifier: Programming Language :: Python :: 3
Requires-Python: >=3.6
License-File: LICENSE
Requires-Dist: aiohttp (>=3.5.4)
Requires-Dist: loguru (>=0.3.2)
Requires-Dist: orjson (>=2.0.7)
